<?xml version="1.0" encoding="UTF-8"?> 
<java version="1.5.0-beta3" class="java.beans.XMLDecoder"> 
 <object class="java.util.ArrayList"> 
  <void method="add"> 
   <object class="goat.weather.User"> 
    <void property="location"> 
     <string>NWWW</string> 
    </void> 
    <void property="name"> 
     <string>bc</string> 
    </void> 
   </object> 
  </void> 
  <void method="add"> 
   <object class="goat.weather.User"> 
    <void property="location"> 
     <string>KDAL</string> 
    </void> 
    <void property="name"> 
     <string>gunnerbobby</string> 
    </void> 
   </object> 
  </void> 
 </object> 
</java> 
